{"id":"819dcdab-4392-4589-a918-884af81eb713","revision":0,"last_node_id":20,"last_link_id":40,"nodes":[{"id":6,"type":"VAEDecode","pos":[1460,70],"size":[300,120],"flags":{},"order":14,"mode":0,"inputs":[{"localized_name":"Latent","name":"samples","type":"LATENT","link":8},{"localized_name":"vae","name":"vae","type":"VAE","link":4}],"outputs":[{"localized_name":"图像","name":"IMAGE","type":"IMAGE","links":[9]}],"properties":{"cnr_id":"comfy-core","ver":"0.3.68","Node name for S&R":"Decode (DPM++ 2M)"},"widgets_values":[]},{"id":9,"type":"VAEDecode","pos":[1460,420],"size":[300,120],"flags":{},"order":15,"mode":0,"inputs":[{"localized_name":"Latent","name":"samples","type":"LATENT","link":11},{"localized_name":"vae","name":"vae","type":"VAE","link":13}],"outputs":[{"localized_name":"图像","name":"IMAGE","type":"IMAGE","links":[12]}],"properties":{"cnr_id":"comfy-core","ver":"0.3.68","Node name for S&R":"Decode (Euler a)"},"widgets_values":[]},{"id":12,"type":"VAEDecode","pos":[1460,780],"size":[300,120],"flags":{},"order":16,"mode":0,"inputs":[{"localized_name":"Latent","name":"samples","type":"LATENT","link":20},{"localized_name":"vae","name":"vae","type":"VAE","link":22}],"outputs":[{"localized_name":"图像","name":"IMAGE","type":"IMAGE","links":[21]}],"properties":{"cnr_id":"comfy-core","ver":"0.3.68","Node name for S&R":"Decode (Euler SMEA approx)"},"widgets_values":[]},{"id":14,"type":"Note","pos":[-444.8369532672375,280],"size":[360,220],"flags":{},"order":0,"mode":0,"inputs":[],"outputs":[],"properties":{},"widgets_values":["AniKawaXL 推荐：Steps 25–30。\n\n• DPM++ 2M：该模型标准/推荐。\n• Euler a：比 DPM++ 2M 更柔和。\n• Euler SMEA：比 Euler a 更柔和、背景更简化（ComfyUI 无原生 SMEA，这里提供近似预设）。\n\nV1：首版；V2：背景更高细节（默认加载 V2 checkpoint）。"],"color":"#432","bgcolor":"#653"},{"id":15,"type":"Note","pos":[-444.8369532672375,530],"size":[360,190],"flags":{},"order":1,"mode":0,"inputs":[],"outputs":[],"properties":{},"widgets_values":["用法：\n1) 修改 Positive prompt 的 <YOUR PROMPT HERE>。\n2) 三个采样器会分别输出 3 张图（便于对比找到你最喜欢的风格）。\n3) 若只想出一张图，禁用/断开另外两个 KSampler 分支即可。"],"color":"#432","bgcolor":"#653"},{"id":5,"type":"KSampler","pos":[960,40],"size":[470,310],"flags":{},"order":11,"mode":0,"inputs":[{"localized_name":"模型","name":"model","type":"MODEL","link":1},{"localized_name":"正面条件","name":"positive","type":"CONDITIONING","link":5},{"localized_name":"负面条件","name":"negative","type":"CONDITIONING","link":6},{"localized_name":"Latent图像","name":"latent_image","type":"LATENT","link":7},{"localized_name":"种子","name":"seed","type":"INT","widget":{"name":"seed"},"link":null},{"localized_name":"步数","name":"steps","type":"INT","widget":{"name":"steps"},"link":null},{"localized_name":"cfg","name":"cfg","type":"FLOAT","widget":{"name":"cfg"},"link":null},{"localized_name":"采样器名称","name":"sampler_name","type":"COMBO","widget":{"name":"sampler_name"},"link":null},{"localized_name":"调度器","name":"scheduler","type":"COMBO","widget":{"name":"scheduler"},"link":null},{"localized_name":"降噪","name":"denoise","type":"FLOAT","widget":{"name":"denoise"},"link":null}],"outputs":[{"localized_name":"Latent","name":"LATENT","type":"LATENT","links":[8]}],"properties":{"cnr_id":"comfy-core","ver":"0.3.68","Node name for S&R":"DPM++ 2M (standard)"},"widgets_values":[770228525173539,"randomize",28,7,"dpmpp_2m","karras",1]},{"id":8,"type":"KSampler","pos":[960,390],"size":[470,310],"flags":{},"order":12,"mode":0,"inputs":[{"localized_name":"模型","name":"model","type":"MODEL","link":10},{"localized_name":"正面条件","name":"positive","type":"CONDITIONING","link":14},{"localized_name":"负面条件","name":"negative","type":"CONDITIONING","link":15},{"localized_name":"Latent图像","name":"latent_image","type":"LATENT","link":16},{"localized_name":"种子","name":"seed","type":"INT","widget":{"name":"seed"},"link":null},{"localized_name":"步数","name":"steps","type":"INT","widget":{"name":"steps"},"link":null},{"localized_name":"cfg","name":"cfg","type":"FLOAT","widget":{"name":"cfg"},"link":null},{"localized_name":"采样器名称","name":"sampler_name","type":"COMBO","widget":{"name":"sampler_name"},"link":null},{"localized_name":"调度器","name":"scheduler","type":"COMBO","widget":{"name":"scheduler"},"link":null},{"localized_name":"降噪","name":"denoise","type":"FLOAT","widget":{"name":"denoise"},"link":null}],"outputs":[{"localized_name":"Latent","name":"LATENT","type":"LATENT","links":[11]}],"properties":{"cnr_id":"comfy-core","ver":"0.3.68","Node name for S&R":"Euler a (softer)"},"widgets_values":[237416680115466,"randomize",28,7,"euler_ancestral","karras",1]},{"id":11,"type":"KSampler","pos":[960,740],"size":[470,330],"flags":{},"order":13,"mode":0,"inputs":[{"localized_name":"模型","name":"model","type":"MODEL","link":19},{"localized_name":"正面条件","name":"positive","type":"CONDITIONING","link":23},{"localized_name":"负面条件","name":"negative","type":"CONDITIONING","link":24},{"localized_name":"Latent图像","name":"latent_image","type":"LATENT","link":25},{"localized_name":"种子","name":"seed","type":"INT","widget":{"name":"seed"},"link":null},{"localized_name":"步数","name":"steps","type":"INT","widget":{"name":"steps"},"link":null},{"localized_name":"cfg","name":"cfg","type":"FLOAT","widget":{"name":"cfg"},"link":null},{"localized_name":"采样器名称","name":"sampler_name","type":"COMBO","widget":{"name":"sampler_name"},"link":null},{"localized_name":"调度器","name":"scheduler","type":"COMBO","widget":{"name":"scheduler"},"link":null},{"localized_name":"降噪","name":"denoise","type":"FLOAT","widget":{"name":"denoise"},"link":null}],"outputs":[{"localized_name":"Latent","name":"LATENT","type":"LATENT","links":[20]}],"properties":{"cnr_id":"comfy-core","ver":"0.3.68","Node name for S&R":"Euler SMEA (approx in ComfyUI)"},"widgets_values":[623077360373552,"randomize",25,6.5,"euler_ancestral","normal",1]},{"id":7,"type":"SaveImage","pos":[1790,70],"size":[280,270],"flags":{},"order":17,"mode":0,"inputs":[{"localized_name":"图片","name":"images","type":"IMAGE","link":9},{"localized_name":"文件名前缀","name":"filename_prefix","type":"STRING","widget":{"name":"filename_prefix"},"link":null}],"outputs":[],"properties":{"cnr_id":"comfy-core","ver":"0.3.68"},"widgets_values":["%date:yyyy-MM-dd%/%date:HH-mm-ss%D"]},{"id":10,"type":"SaveImage","pos":[1790,420],"size":[280,270],"flags":{},"order":18,"mode":0,"inputs":[{"localized_name":"图片","name":"images","type":"IMAGE","link":12},{"localized_name":"文件名前缀","name":"filename_prefix","type":"STRING","widget":{"name":"filename_prefix"},"link":null}],"outputs":[],"properties":{"cnr_id":"comfy-core","ver":"0.3.68"},"widgets_values":["%date:yyyy-MM-dd%/%date:HH-mm-ss%E"]},{"id":13,"type":"SaveImage","pos":[1790,780],"size":[280,270],"flags":{},"order":19,"mode":0,"inputs":[{"localized_name":"图片","name":"images","type":"IMAGE","link":21},{"localized_name":"文件名前缀","name":"filename_prefix","type":"STRING","widget":{"name":"filename_prefix"},"link":null}],"outputs":[],"properties":{"cnr_id":"comfy-core","ver":"0.3.68"},"widgets_values":["%date:yyyy-MM-dd%/%date:HH-mm-ss%A"]},{"id":1,"type":"CheckpointLoaderSimple","pos":[-444.8369532672375,120],"size":[360,120],"flags":{},"order":2,"mode":0,"inputs":[{"localized_name":"Checkpoint名称","name":"ckpt_name","type":"COMBO","widget":{"name":"ckpt_name"},"link":null}],"outputs":[{"localized_name":"模型","name":"MODEL","type":"MODEL","links":[31]},{"localized_name":"CLIP","name":"CLIP","type":"CLIP","links":[32]},{"localized_name":"VAE","name":"VAE","type":"VAE","links":[4,13,22]}],"properties":{"cnr_id":"comfy-core","ver":"0.3.68","Node name for S&R":"AniKawaXL checkpoint (V1/V2)"},"widgets_values":["anikawaxl_v2.safetensors"]},{"id":17,"type":"LoraLoader","pos":[-14.83695326723755,230],"size":[360,126],"flags":{},"order":5,"mode":4,"inputs":[{"localized_name":"模型","name":"model","type":"MODEL","link":33},{"localized_name":"CLIPCLIP","name":"clip","type":"CLIP","link":34},{"localized_name":"LoRA名称","name":"lora_name","type":"COMBO","widget":{"name":"lora_name"},"link":null},{"localized_name":"模型强度","name":"strength_model","type":"FLOAT","widget":{"name":"strength_model"},"link":null},{"localized_name":"CLIP强度","name":"strength_clip","type":"FLOAT","widget":{"name":"strength_clip"},"link":null}],"outputs":[{"localized_name":"模型","name":"MODEL","type":"MODEL","links":[35]},{"localized_name":"CLIP","name":"CLIP","type":"CLIP","links":[36]}],"properties":{"cnr_id":"comfy-core","ver":"0.3.75","Node name for S&R":"LoRA 2"},"widgets_values":["lightx2v_I2V_14B_480p_cfg_step_distill_rank128_bf16.safetensors",1,1]},{"id":16,"type":"LoraLoader","pos":[-14.83695326723755,80],"size":[360,126],"flags":{},"order":4,"mode":4,"inputs":[{"localized_name":"模型","name":"model","type":"MODEL","link":31},{"localized_name":"CLIPCLIP","name":"clip","type":"CLIP","link":32},{"localized_name":"LoRA名称","name":"lora_name","type":"COMBO","widget":{"name":"lora_name"},"link":null},{"localized_name":"模型强度","name":"strength_model","type":"FLOAT","widget":{"name":"strength_model"},"link":null},{"localized_name":"CLIP强度","name":"strength_clip","type":"FLOAT","widget":{"name":"strength_clip"},"link":null}],"outputs":[{"localized_name":"模型","name":"MODEL","type":"MODEL","links":[33]},{"localized_name":"CLIP","name":"CLIP","type":"CLIP","links":[34]}],"properties":{"cnr_id":"comfy-core","ver":"0.3.75","Node name for S&R":"LoRA 1"},"widgets_values":["",1,1]},{"id":18,"type":"LoraLoader","pos":[-14.83695326723755,400],"size":[360,126],"flags":{},"order":6,"mode":4,"inputs":[{"localized_name":"模型","name":"model","type":"MODEL","link":35},{"localized_name":"CLIPCLIP","name":"clip","type":"CLIP","link":36},{"localized_name":"LoRA名称","name":"lora_name","type":"COMBO","widget":{"name":"lora_name"},"link":null},{"localized_name":"模型强度","name":"strength_model","type":"FLOAT","widget":{"name":"strength_model"},"link":null},{"localized_name":"CLIP强度","name":"strength_clip","type":"FLOAT","widget":{"name":"strength_clip"},"link":null}],"outputs":[{"localized_name":"模型","name":"MODEL","type":"MODEL","links":[37]},{"localized_name":"CLIP","name":"CLIP","type":"CLIP","links":[38]}],"properties":{"cnr_id":"comfy-core","ver":"0.3.75","Node name for S&R":"LoRA 3"},"widgets_values":["",1,1]},{"id":19,"type":"LoraLoader","pos":[-14.83695326723755,560],"size":[360,126],"flags":{},"order":7,"mode":4,"inputs":[{"localized_name":"模型","name":"model","type":"MODEL","link":37},{"localized_name":"CLIPCLIP","name":"clip","type":"CLIP","link":38},{"localized_name":"LoRA名称","name":"lora_name","type":"COMBO","widget":{"name":"lora_name"},"link":null},{"localized_name":"模型强度","name":"strength_model","type":"FLOAT","widget":{"name":"strength_model"},"link":null},{"localized_name":"CLIP强度","name":"strength_clip","type":"FLOAT","widget":{"name":"strength_clip"},"link":null}],"outputs":[{"localized_name":"模型","name":"MODEL","type":"MODEL","links":[39]},{"localized_name":"CLIP","name":"CLIP","type":"CLIP","links":[40]}],"properties":{"cnr_id":"comfy-core","ver":"0.3.75","Node name for S&R":"LoRA 4"},"widgets_values":["",1,1]},{"id":20,"type":"LoraLoader","pos":[-14.83695326723755,720],"size":[360,126],"flags":{},"order":8,"mode":0,"inputs":[{"localized_name":"模型","name":"model","type":"MODEL","link":39},{"localized_name":"CLIPCLIP","name":"clip","type":"CLIP","link":40},{"localized_name":"LoRA名称","name":"lora_name","type":"COMBO","widget":{"name":"lora_name"},"link":null},{"localized_name":"模型强度","name":"strength_model","type":"FLOAT","widget":{"name":"strength_model"},"link":null},{"localized_name":"CLIP强度","name":"strength_clip","type":"FLOAT","widget":{"name":"strength_clip"},"link":null}],"outputs":[{"localized_name":"模型","name":"MODEL","type":"MODEL","links":[1,10,19]},{"localized_name":"CLIP","name":"CLIP","type":"CLIP","links":[2,3]}],"properties":{"cnr_id":"comfy-core","ver":"0.3.75","Node name for S&R":"LoRA 5"},"widgets_values":["NoobaiVpred10Insertion_vpred10V2.safetensors",3,3]},{"id":3,"type":"CLIPTextEncode","pos":[423.14733967218217,458.98898937321434],"size":[460,240],"flags":{},"order":10,"mode":0,"inputs":[{"localized_name":"clip","name":"clip","type":"CLIP","link":3},{"localized_name":"文本","name":"text","type":"STRING","widget":{"name":"text"},"link":null}],"outputs":[{"localized_name":"条件","name":"CONDITIONING","type":"CONDITIONING","links":[6,15,24]}],"properties":{"cnr_id":"comfy-core","ver":"0.3.68","Node name for S&R":"Negative prompt"},"widgets_values":["2girls, multiple girls, duplicate character, cloned face, extra person, additional girl, girl in background, female in crowd, lowres, bad anatomy, multiple views"]},{"id":4,"type":"EmptyLatentImage","pos":[477.731119129077,775.0497865811992],"size":[320,120],"flags":{},"order":3,"mode":0,"inputs":[{"localized_name":"宽度","name":"width","type":"INT","widget":{"name":"width"},"link":null},{"localized_name":"高度","name":"height","type":"INT","widget":{"name":"height"},"link":null},{"localized_name":"批量大小","name":"batch_size","type":"INT","widget":{"name":"batch_size"},"link":null}],"outputs":[{"localized_name":"Latent","name":"LATENT","type":"LATENT","links":[7,16,25]}],"properties":{"cnr_id":"comfy-core","ver":"0.3.68","Node name for S&R":"Latent (SDXL base res)"},"widgets_values":[1024,1536,1]},{"id":2,"type":"CLIPTextEncode","pos":[423.14733967218217,208.9889893732144],"size":[460,220],"flags":{},"order":9,"mode":0,"inputs":[{"localized_name":"clip","name":"clip","type":"CLIP","link":2},{"localized_name":"文本","name":"text","type":"STRING","widget":{"name":"text"},"link":null}],"outputs":[{"localized_name":"条件","name":"CONDITIONING","type":"CONDITIONING","links":[5,14,23]}],"properties":{"cnr_id":"comfy-core","ver":"0.3.68","Node name for S&R":"Positive prompt"},"widgets_values":["1girl, (konjiki no yami), nfsw, masterpiece, 8k resolution, glaring, blush, chain, clothes lift, cloud, water, lake, collar, contrail, cowboy shot, day, dress lift, exhibitionism, blonde hair, lifting own clothes, navel, no panties, o-ring collar, outdoors, public indecency, public nudity, pussy, pussy juice, shackles, sky, solo, flower, uncensored, (vaginal object insertion, dildo, spread pussy, tape), stomach bulge, trembling, motion lines, twitching, orgasm, female orgasm, shaded_face\n"]}],"links":[[1,20,0,5,0,"MODEL"],[2,20,1,2,0,"CLIP"],[3,20,1,3,0,"CLIP"],[4,1,2,6,1,"VAE"],[5,2,0,5,1,"CONDITIONING"],[6,3,0,5,2,"CONDITIONING"],[7,4,0,5,3,"LATENT"],[8,5,0,6,0,"LATENT"],[9,6,0,7,0,"IMAGE"],[10,20,0,8,0,"MODEL"],[11,8,0,9,0,"LATENT"],[12,9,0,10,0,"IMAGE"],[13,1,2,9,1,"VAE"],[14,2,0,8,1,"CONDITIONING"],[15,3,0,8,2,"CONDITIONING"],[16,4,0,8,3,"LATENT"],[19,20,0,11,0,"MODEL"],[20,11,0,12,0,"LATENT"],[21,12,0,13,0,"IMAGE"],[22,1,2,12,1,"VAE"],[23,2,0,11,1,"CONDITIONING"],[24,3,0,11,2,"CONDITIONING"],[25,4,0,11,3,"LATENT"],[31,1,0,16,0,"MODEL"],[32,1,1,16,1,"CLIP"],[33,16,0,17,0,"MODEL"],[34,16,1,17,1,"CLIP"],[35,17,0,18,0,"MODEL"],[36,17,1,18,1,"CLIP"],[37,18,0,19,0,"MODEL"],[38,18,1,19,1,"CLIP"],[39,19,0,20,0,"MODEL"],[40,19,1,20,1,"CLIP"]],"groups":[],"config":{},"extra":{"ds":{"scale":0.9229599817706508,"offset":[506.9619496297146,208.23381104772898]},"workflowRendererVersion":"LG","workflow_name":"AniKawaXL (SDXL) — recommended samplers comparison"},"version":0.4}